{"title":"Emerald Imperium 1.3","generatedAt":"2026-04-16T14:27:18.912190Z","historyLimit":100,"trainer":{"displayName":"Sailor Dwayne 3 Badges","usageKey":"Sailor Dwayne 3 Badges","leadLevel":null,"maxLevel":null,"isBoss":false,"partySize":0,"trId":null},"summary":{"totalBattles":6,"topPokemon":[{"species":"Luxray","inParty":2,"caughtCount":3,"participationPct":67,"moves":[{"name":"Thunder Fang","count":2,"pct":100},{"name":"Volt Switch","count":2,"pct":100},{"name":"Crunch","count":1,"pct":50},{"name":"Ice Fang","count":1,"pct":50},{"name":"Psychic Fangs","count":1,"pct":50},{"name":"Sucker Punch","count":1,"pct":50}],"items":[{"name":"Luxrite","count":1,"pct":50},{"name":"Shuca Berry","count":1,"pct":50}],"abilities":[{"name":"Intimidate","count":2,"pct":100}],"natures":[{"name":"Adamant","count":2,"pct":100}]},{"species":"Braviary-Hisui","inParty":1,"caughtCount":1,"participationPct":100,"moves":[{"name":"Air Slash","count":1,"pct":100},{"name":"Aura Sphere","count":1,"pct":100},{"name":"Esper Wing","count":1,"pct":100},{"name":"U-turn","count":1,"pct":100}],"items":[{"name":"Charti Berry","count":1,"pct":100}],"abilities":[{"name":"Tablets of Ruin","count":1,"pct":100}],"natures":[{"name":"Modest","count":1,"pct":100}]},{"species":"Clodsire","inParty":1,"caughtCount":1,"participationPct":100,"moves":[{"name":"Earthquake","count":1,"pct":100},{"name":"Rock Slide","count":1,"pct":100},{"name":"Toxic","count":1,"pct":100},{"name":"Toxic Spikes","count":1,"pct":100}],"items":[{"name":"Black Sludge","count":1,"pct":100}],"abilities":[{"name":"Water Absorb","count":1,"pct":100}],"natures":[{"name":"Careful","count":1,"pct":100}]},{"species":"Conkeldurr","inParty":1,"caughtCount":2,"participationPct":50,"moves":[{"name":"Drain Punch","count":1,"pct":100},{"name":"Low Kick","count":1,"pct":100},{"name":"Mach Punch","count":1,"pct":100},{"name":"Rock Tomb","count":1,"pct":100}],"items":[{"name":"Payapa Berry","count":1,"pct":100}],"abilities":[{"name":"Primordial Sea","count":1,"pct":100}],"natures":[{"name":"Adamant","count":1,"pct":100}]},{"species":"Copperajah","inParty":1,"caughtCount":1,"participationPct":100,"moves":[{"name":"Body Press","count":1,"pct":100},{"name":"Bulldoze","count":1,"pct":100},{"name":"Heavy Slam","count":1,"pct":100},{"name":"Rock Tomb","count":1,"pct":100}],"items":[{"name":"Chople Berry","count":1,"pct":100}],"abilities":[{"name":"Gorilla Tactics","count":1,"pct":100}],"natures":[{"name":"Adamant","count":1,"pct":100}]},{"species":"Dragalge","inParty":1,"caughtCount":1,"participationPct":100,"moves":[{"name":"Feint Attack","count":1,"pct":100},{"name":"Hydro Pump","count":1,"pct":100},{"name":"Sludge Bomb","count":1,"pct":100},{"name":"Water Pulse","count":1,"pct":100}],"items":[{"name":"Black Sludge","count":1,"pct":100}],"abilities":[{"name":"Adaptability","count":1,"pct":100}],"natures":[{"name":"Modest","count":1,"pct":100}]},{"species":"Eldegoss","inParty":1,"caughtCount":1,"participationPct":100,"moves":[{"name":"Cotton Spore","count":1,"pct":100},{"name":"Giga Drain","count":1,"pct":100},{"name":"Hyper Voice","count":1,"pct":100},{"name":"Synthesis","count":1,"pct":100}],"items":[{"name":"Sitrus Berry","count":1,"pct":100}],"abilities":[{"name":"Regenerator","count":1,"pct":100}],"natures":[{"name":"Relaxed","count":1,"pct":100}]},{"species":"Exploud","inParty":1,"caughtCount":1,"participationPct":100,"moves":[{"name":"Bulldoze","count":1,"pct":100},{"name":"Crunch","count":1,"pct":100},{"name":"Fire Fang","count":1,"pct":100},{"name":"Hyper Voice","count":1,"pct":100}],"items":[{"name":"Sitrus Berry","count":1,"pct":100}],"abilities":[{"name":"Soundproof","count":1,"pct":100}],"natures":[{"name":"Modest","count":1,"pct":100}]},{"species":"Giratina","inParty":1,"caughtCount":1,"participationPct":100,"moves":[{"name":"Earth Power","count":1,"pct":100},{"name":"Protect","count":1,"pct":100},{"name":"Psychic","count":1,"pct":100},{"name":"Shadow Ball","count":1,"pct":100}],"items":[{"name":"Leftovers","count":1,"pct":100}],"abilities":[{"name":"Pressure","count":1,"pct":100}],"natures":[{"name":"Modest","count":1,"pct":100}]},{"species":"Golisopod","inParty":1,"caughtCount":2,"participationPct":50,"moves":[{"name":"First Impression","count":1,"pct":100},{"name":"Leech Life","count":1,"pct":100},{"name":"Razor Shell","count":1,"pct":100},{"name":"Sucker Punch","count":1,"pct":100}],"items":[{"name":"Sitrus Berry","count":1,"pct":100}],"abilities":[{"name":"Emergency Exit","count":1,"pct":100}],"natures":[{"name":"Careful","count":1,"pct":100}]},{"species":"Granbull","inParty":1,"caughtCount":2,"participationPct":50,"moves":[{"name":"Fire Fang","count":1,"pct":100},{"name":"Jaw Lock","count":1,"pct":100},{"name":"Play Rough","count":1,"pct":100},{"name":"Thunder Fang","count":1,"pct":100}],"items":[{"name":"Sitrus Berry","count":1,"pct":100}],"abilities":[{"name":"Intimidate","count":1,"pct":100}],"natures":[{"name":"Adamant","count":1,"pct":100}]},{"species":"Gyarados","inParty":1,"caughtCount":2,"participationPct":50,"moves":[{"name":"Aqua Tail","count":1,"pct":100},{"name":"Bulldoze","count":1,"pct":100},{"name":"Crunch","count":1,"pct":100},{"name":"Ice Fang","count":1,"pct":100}],"items":[{"name":"Sitrus Berry","count":1,"pct":100}],"abilities":[{"name":"Intimidate","count":1,"pct":100}],"natures":[{"name":"Adamant","count":1,"pct":100}]},{"species":"Heliolisk","inParty":1,"caughtCount":1,"participationPct":100,"moves":[{"name":"Hyper Voice","count":1,"pct":100},{"name":"Parabolic Charge","count":1,"pct":100},{"name":"Thunderbolt","count":1,"pct":100},{"name":"Volt Switch","count":1,"pct":100}],"items":[{"name":"Magnet","count":1,"pct":100}],"abilities":[{"name":"Dry Skin","count":1,"pct":100}],"natures":[{"name":"Timid","count":1,"pct":100}]},{"species":"Kilowattrel","inParty":1,"caughtCount":1,"participationPct":100,"moves":[{"name":"Air Slash","count":1,"pct":100},{"name":"Roost","count":1,"pct":100},{"name":"Thunder Shock","count":1,"pct":100},{"name":"Volt Switch","count":1,"pct":100}],"items":[{"name":"Sharp Beak","count":1,"pct":100}],"abilities":[{"name":"Volt Absorb","count":1,"pct":100}],"natures":[{"name":"Modest","count":1,"pct":100}]},{"species":"Lapras","inParty":1,"caughtCount":1,"participationPct":100,"moves":[{"name":"Dragon Pulse","count":1,"pct":100},{"name":"Ice Shard","count":1,"pct":100},{"name":"Scald","count":1,"pct":100},{"name":"Wish","count":1,"pct":100}],"items":[{"name":"Leftovers","count":1,"pct":100}],"abilities":[{"name":"Water Absorb","count":1,"pct":100}],"natures":[{"name":"Modest","count":1,"pct":100}]},{"species":"Lilligant-Hisui","inParty":1,"caughtCount":1,"participationPct":100,"moves":[{"name":"Drain Punch","count":1,"pct":100},{"name":"Leaf Blade","count":1,"pct":100},{"name":"Recover","count":1,"pct":100},{"name":"Sleep Powder","count":1,"pct":100}],"items":[{"name":"Chilan Berry","count":1,"pct":100}],"abilities":[{"name":"Chlorophyll","count":1,"pct":100}],"natures":[{"name":"Jolly","count":1,"pct":100}]},{"species":"Luxray-Mega","inParty":1,"caughtCount":1,"participationPct":100,"moves":[{"name":"Psychic Fangs","count":1,"pct":100},{"name":"Sucker Punch","count":1,"pct":100},{"name":"Thunder Fang","count":1,"pct":100},{"name":"Volt Switch","count":1,"pct":100}],"items":[],"abilities":[{"name":"Strong Jaw","count":1,"pct":100}],"natures":[{"name":"Adamant","count":1,"pct":100}]},{"species":"Magnezone","inParty":1,"caughtCount":1,"participationPct":100,"moves":[{"name":"Flash Cannon","count":1,"pct":100},{"name":"Reflect","count":1,"pct":100},{"name":"Thunderbolt","count":1,"pct":100},{"name":"Volt Switch","count":1,"pct":100}],"items":[{"name":"Chople Berry","count":1,"pct":100}],"abilities":[{"name":"Analytic","count":1,"pct":100}],"natures":[{"name":"Modest","count":1,"pct":100}]},{"species":"Meowscarada","inParty":1,"caughtCount":2,"participationPct":50,"moves":[{"name":"Flower Trick","count":1,"pct":100},{"name":"Play Rough","count":1,"pct":100},{"name":"Protect","count":1,"pct":100},{"name":"U-turn","count":1,"pct":100}],"items":[{"name":"Miracle Seed","count":1,"pct":100}],"abilities":[{"name":"Protean","count":1,"pct":100}],"natures":[{"name":"Jolly","count":1,"pct":100}]},{"species":"Minun","inParty":1,"caughtCount":1,"participationPct":100,"moves":[{"name":"Double-Edge","count":1,"pct":100},{"name":"Encore","count":1,"pct":100},{"name":"Nuzzle","count":1,"pct":100},{"name":"Quick Attack","count":1,"pct":100}],"items":[{"name":"Magnet","count":1,"pct":100}],"abilities":[{"name":"Galvanize","count":1,"pct":100}],"natures":[{"name":"Jolly","count":1,"pct":100}]},{"species":"Mudsdale","inParty":1,"caughtCount":2,"participationPct":50,"moves":[{"name":"Bulldoze","count":1,"pct":100},{"name":"Earthquake","count":1,"pct":100},{"name":"Heavy Slam","count":1,"pct":100},{"name":"Rock Slide","count":1,"pct":100}],"items":[{"name":"Sitrus Berry","count":1,"pct":100}],"abilities":[{"name":"Stamina","count":1,"pct":100}],"natures":[{"name":"Adamant","count":1,"pct":100}]},{"species":"Pikachu-Flying","inParty":1,"caughtCount":1,"participationPct":100,"moves":[{"name":"Air Slash","count":1,"pct":100},{"name":"Fake Out","count":1,"pct":100},{"name":"Nuzzle","count":1,"pct":100},{"name":"Thunderbolt","count":1,"pct":100}],"items":[{"name":"Light Ball","count":1,"pct":100}],"abilities":[{"name":"Static","count":1,"pct":100}],"natures":[{"name":"Timid","count":1,"pct":100}]},{"species":"Primarina","inParty":1,"caughtCount":1,"participationPct":100,"moves":[{"name":"Encore","count":1,"pct":100},{"name":"Flip Turn","count":1,"pct":100},{"name":"Hyper Voice","count":1,"pct":100},{"name":"Moonblast","count":1,"pct":100}],"items":[{"name":"Sitrus Berry","count":1,"pct":100}],"abilities":[{"name":"Liquid Voice","count":1,"pct":100}],"natures":[{"name":"Calm","count":1,"pct":100}]},{"species":"Qwilfish","inParty":1,"caughtCount":1,"participationPct":100,"moves":[{"name":"Barb Barrage","count":1,"pct":100},{"name":"Bubble","count":1,"pct":100},{"name":"Revenge","count":1,"pct":100},{"name":"Tackle","count":1,"pct":100}],"items":[{"name":"Sitrus Berry","count":1,"pct":100}],"abilities":[{"name":"Intimidate","count":1,"pct":100}],"natures":[{"name":"Adamant","count":1,"pct":100}]},{"species":"Rhyperior","inParty":1,"caughtCount":1,"participationPct":100,"moves":[{"name":"Bulldoze","count":1,"pct":100},{"name":"Earthquake","count":1,"pct":100},{"name":"Hammer Arm","count":1,"pct":100},{"name":"Rock Slide","count":1,"pct":100}],"items":[{"name":"Sitrus Berry","count":1,"pct":100}],"abilities":[{"name":"Solid Rock","count":1,"pct":100}],"natures":[{"name":"Adamant","count":1,"pct":100}]},{"species":"Scizor","inParty":1,"caughtCount":1,"participationPct":100,"moves":[{"name":"Bullet Punch","count":1,"pct":100},{"name":"Iron Head","count":1,"pct":100},{"name":"Pounce","count":1,"pct":100},{"name":"Protect","count":1,"pct":100}],"items":[{"name":"Sitrus Berry","count":1,"pct":100}],"abilities":[{"name":"Technician","count":1,"pct":100}],"natures":[{"name":"Adamant","count":1,"pct":100}]},{"species":"Scyther","inParty":1,"caughtCount":1,"participationPct":100,"moves":[{"name":"Brick Break","count":1,"pct":100},{"name":"Psycho Cut","count":1,"pct":100},{"name":"U-turn","count":1,"pct":100},{"name":"Wing Attack","count":1,"pct":100}],"items":[{"name":"Eviolite","count":1,"pct":100}],"abilities":[{"name":"Fur Coat","count":1,"pct":100}],"natures":[{"name":"Adamant","count":1,"pct":100}]},{"species":"Skarmory","inParty":1,"caughtCount":1,"participationPct":100,"moves":[{"name":"Dual Wingbeat","count":1,"pct":100},{"name":"Roost","count":1,"pct":100},{"name":"Slash","count":1,"pct":100},{"name":"Steel Wing","count":1,"pct":100}],"items":[],"abilities":[{"name":"Sturdy","count":1,"pct":100}],"natures":[{"name":"Naive","count":1,"pct":100}]},{"species":"Slaking","inParty":1,"caughtCount":1,"participationPct":100,"moves":[{"name":"Body Slam","count":1,"pct":100},{"name":"Hammer Arm","count":1,"pct":100},{"name":"Slack Off","count":1,"pct":100},{"name":"Sucker Punch","count":1,"pct":100}],"items":[{"name":"Silk Scarf","count":1,"pct":100}],"abilities":[{"name":"Shadow Shield","count":1,"pct":100}],"natures":[{"name":"Adamant","count":1,"pct":100}]},{"species":"Slowbro","inParty":1,"caughtCount":4,"participationPct":25,"moves":[{"name":"Psychic","count":1,"pct":100},{"name":"Scald","count":1,"pct":100},{"name":"Slack Off","count":1,"pct":100},{"name":"Toxic","count":1,"pct":100}],"items":[{"name":"Leftovers","count":1,"pct":100}],"abilities":[{"name":"Regenerator","count":1,"pct":100}],"natures":[{"name":"Bold","count":1,"pct":100}]},{"species":"Stunfisk","inParty":1,"caughtCount":3,"participationPct":33,"moves":[{"name":"Mud Shot","count":1,"pct":100},{"name":"Rest","count":1,"pct":100},{"name":"Scald","count":1,"pct":100},{"name":"Thunderbolt","count":1,"pct":100}],"items":[{"name":"Sitrus Berry","count":1,"pct":100}],"abilities":[{"name":"Static","count":1,"pct":100}],"natures":[{"name":"Bold","count":1,"pct":100}]},{"species":"Swanna","inParty":1,"caughtCount":3,"participationPct":33,"moves":[{"name":"Flip Turn","count":1,"pct":100},{"name":"Hurricane","count":1,"pct":100},{"name":"Hydro Pump","count":1,"pct":100},{"name":"Roost","count":1,"pct":100}],"items":[{"name":"Sitrus Berry","count":1,"pct":100}],"abilities":[{"name":"No Guard","count":1,"pct":100}],"natures":[{"name":"Timid","count":1,"pct":100}]},{"species":"Tinkaton","inParty":1,"caughtCount":2,"participationPct":50,"moves":[{"name":"Fake Out","count":1,"pct":100},{"name":"Gigaton Hammer","count":1,"pct":100},{"name":"Play Rough","count":1,"pct":100},{"name":"Rock Slide","count":1,"pct":100}],"items":[{"name":"Leftovers","count":1,"pct":100}],"abilities":[{"name":"Mold Breaker","count":1,"pct":100}],"natures":[{"name":"Adamant","count":1,"pct":100}]},{"species":"Torterra","inParty":1,"caughtCount":3,"participationPct":33,"moves":[{"name":"Earthquake","count":1,"pct":100},{"name":"Rock Slide","count":1,"pct":100},{"name":"Synthesis","count":1,"pct":100},{"name":"Wood Hammer","count":1,"pct":100}],"items":[{"name":"Tanga Berry","count":1,"pct":100}],"abilities":[{"name":"Shell Armor","count":1,"pct":100}],"natures":[{"name":"Adamant","count":1,"pct":100}]},{"species":"Zebstrika","inParty":1,"caughtCount":1,"participationPct":100,"moves":[{"name":"Discharge","count":1,"pct":100},{"name":"Flame Wheel","count":1,"pct":100},{"name":"Spark","count":1,"pct":100},{"name":"Thunder Wave","count":1,"pct":100}],"items":[{"name":"Sitrus Berry","count":1,"pct":100}],"abilities":[{"name":"Lightning Rod","count":1,"pct":100}],"natures":[{"name":"Jolly","count":1,"pct":100}]},{"species":"Altaria","inParty":0,"caughtCount":1,"participationPct":0,"moves":[],"items":[],"abilities":[],"natures":[]},{"species":"Annihilape","inParty":0,"caughtCount":1,"participationPct":0,"moves":[],"items":[],"abilities":[],"natures":[]},{"species":"Araquanid","inParty":0,"caughtCount":1,"participationPct":0,"moves":[],"items":[],"abilities":[],"natures":[]},{"species":"Barboach","inParty":0,"caughtCount":1,"participationPct":0,"moves":[],"items":[],"abilities":[],"natures":[]},{"species":"Beedrill","inParty":0,"caughtCount":2,"participationPct":0,"moves":[],"items":[],"abilities":[],"natures":[]},{"species":"Bibarel","inParty":0,"caughtCount":1,"participationPct":0,"moves":[],"items":[],"abilities":[],"natures":[]},{"species":"Bisharp","inParty":0,"caughtCount":1,"participationPct":0,"moves":[],"items":[],"abilities":[],"natures":[]},{"species":"Blastoise","inParty":0,"caughtCount":2,"participationPct":0,"moves":[],"items":[],"abilities":[],"natures":[]},{"species":"Breloom","inParty":0,"caughtCount":1,"participationPct":0,"moves":[],"items":[],"abilities":[],"natures":[]},{"species":"Bronzong","inParty":0,"caughtCount":1,"participationPct":0,"moves":[],"items":[],"abilities":[],"natures":[]},{"species":"Butterfree","inParty":0,"caughtCount":1,"participationPct":0,"moves":[],"items":[],"abilities":[],"natures":[]},{"species":"Cacturne","inParty":0,"caughtCount":1,"participationPct":0,"moves":[],"items":[],"abilities":[],"natures":[]},{"species":"Camerupt","inParty":0,"caughtCount":1,"participationPct":0,"moves":[],"items":[],"abilities":[],"natures":[]},{"species":"Centiskorch","inParty":0,"caughtCount":1,"participationPct":0,"moves":[],"items":[],"abilities":[],"natures":[]},{"species":"Chesnaught","inParty":0,"caughtCount":1,"participationPct":0,"moves":[],"items":[],"abilities":[],"natures":[]},{"species":"Chimchar","inParty":0,"caughtCount":1,"participationPct":0,"moves":[],"items":[],"abilities":[],"natures":[]},{"species":"Cinderace","inParty":0,"caughtCount":1,"participationPct":0,"moves":[],"items":[],"abilities":[],"natures":[]},{"species":"Corsola","inParty":0,"caughtCount":1,"participationPct":0,"moves":[],"items":[],"abilities":[],"natures":[]},{"species":"Cubchoo","inParty":0,"caughtCount":1,"participationPct":0,"moves":[],"items":[],"abilities":[],"natures":[]},{"species":"Darmanitan","inParty":0,"caughtCount":1,"participationPct":0,"moves":[],"items":[],"abilities":[],"natures":[]},{"species":"Delibird","inParty":0,"caughtCount":1,"participationPct":0,"moves":[],"items":[],"abilities":[],"natures":[]},{"species":"Delphox","inParty":0,"caughtCount":2,"participationPct":0,"moves":[],"items":[],"abilities":[],"natures":[]},{"species":"Dewgong","inParty":0,"caughtCount":2,"participationPct":0,"moves":[],"items":[],"abilities":[],"natures":[]},{"species":"Drifblim","inParty":0,"caughtCount":1,"participationPct":0,"moves":[],"items":[],"abilities":[],"natures":[]},{"species":"Dubwool","inParty":0,"caughtCount":1,"participationPct":0,"moves":[],"items":[],"abilities":[],"natures":[]},{"species":"Ducklett","inParty":0,"caughtCount":1,"participationPct":0,"moves":[],"items":[],"abilities":[],"natures":[]},{"species":"Electabuzz","inParty":0,"caughtCount":1,"participationPct":0,"moves":[],"items":[],"abilities":[],"natures":[]},{"species":"Electivire","inParty":0,"caughtCount":2,"participationPct":0,"moves":[],"items":[],"abilities":[],"natures":[]},{"species":"Emboar","inParty":0,"caughtCount":1,"participationPct":0,"moves":[],"items":[],"abilities":[],"natures":[]},{"species":"Empoleon","inParty":0,"caughtCount":1,"participationPct":0,"moves":[],"items":[],"abilities":[],"natures":[]},{"species":"Escavalier","inParty":0,"caughtCount":1,"participationPct":0,"moves":[],"items":[],"abilities":[],"natures":[]},{"species":"Fearow","inParty":0,"caughtCount":1,"participationPct":0,"moves":[],"items":[],"abilities":[],"natures":[]},{"species":"Ferrothorn","inParty":0,"caughtCount":1,"participationPct":0,"moves":[],"items":[],"abilities":[],"natures":[]},{"species":"Flygon","inParty":0,"caughtCount":1,"participationPct":0,"moves":[],"items":[],"abilities":[],"natures":[]},{"species":"Foongus","inParty":0,"caughtCount":1,"participationPct":0,"moves":[],"items":[],"abilities":[],"natures":[]},{"species":"Froslass","inParty":0,"caughtCount":1,"participationPct":0,"moves":[],"items":[],"abilities":[],"natures":[]},{"species":"Furret","inParty":0,"caughtCount":1,"participationPct":0,"moves":[],"items":[],"abilities":[],"natures":[]},{"species":"Galvantula","inParty":0,"caughtCount":1,"participationPct":0,"moves":[],"items":[],"abilities":[],"natures":[]},{"species":"Gardevoir","inParty":0,"caughtCount":2,"participationPct":0,"moves":[],"items":[],"abilities":[],"natures":[]},{"species":"Gastly","inParty":0,"caughtCount":1,"participationPct":0,"moves":[],"items":[],"abilities":[],"natures":[]},{"species":"Gengar","inParty":0,"caughtCount":2,"participationPct":0,"moves":[],"items":[],"abilities":[],"natures":[]},{"species":"Gigalith","inParty":0,"caughtCount":1,"participationPct":0,"moves":[],"items":[],"abilities":[],"natures":[]},{"species":"Glastrier","inParty":0,"caughtCount":1,"participationPct":0,"moves":[],"items":[],"abilities":[],"natures":[]},{"species":"Golem","inParty":0,"caughtCount":1,"participationPct":0,"moves":[],"items":[],"abilities":[],"natures":[]},{"species":"Greninja","inParty":0,"caughtCount":1,"participationPct":0,"moves":[],"items":[],"abilities":[],"natures":[]},{"species":"Grotle","inParty":0,"caughtCount":1,"participationPct":0,"moves":[],"items":[],"abilities":[],"natures":[]},{"species":"Grumpig","inParty":0,"caughtCount":1,"participationPct":0,"moves":[],"items":[],"abilities":[],"natures":[]},{"species":"Hatterene","inParty":0,"caughtCount":1,"participationPct":0,"moves":[],"items":[],"abilities":[],"natures":[]},{"species":"Haunter","inParty":0,"caughtCount":1,"participationPct":0,"moves":[],"items":[],"abilities":[],"natures":[]},{"species":"Heatmor","inParty":0,"caughtCount":1,"participationPct":0,"moves":[],"items":[],"abilities":[],"natures":[]},{"species":"Heracross","inParty":0,"caughtCount":1,"participationPct":0,"moves":[],"items":[],"abilities":[],"natures":[]},{"species":"Horsea","inParty":0,"caughtCount":1,"participationPct":0,"moves":[],"items":[],"abilities":[],"natures":[]},{"species":"Illumise","inParty":0,"caughtCount":1,"participationPct":0,"moves":[],"items":[],"abilities":[],"natures":[]},{"species":"Incineroar","inParty":0,"caughtCount":1,"participationPct":0,"moves":[],"items":[],"abilities":[],"natures":[]},{"species":"Inkay","inParty":0,"caughtCount":1,"participationPct":0,"moves":[],"items":[],"abilities":[],"natures":[]},{"species":"Inteleon","inParty":0,"caughtCount":1,"participationPct":0,"moves":[],"items":[],"abilities":[],"natures":[]},{"species":"Kricketune","inParty":0,"caughtCount":1,"participationPct":0,"moves":[],"items":[],"abilities":[],"natures":[]},{"species":"Krookodile","inParty":0,"caughtCount":1,"participationPct":0,"moves":[],"items":[],"abilities":[],"natures":[]},{"species":"Leavanny","inParty":0,"caughtCount":1,"participationPct":0,"moves":[],"items":[],"abilities":[],"natures":[]},{"species":"Lechonk","inParty":0,"caughtCount":1,"participationPct":0,"moves":[],"items":[],"abilities":[],"natures":[]},{"species":"Ludicolo","inParty":0,"caughtCount":1,"participationPct":0,"moves":[],"items":[],"abilities":[],"natures":[]},{"species":"Machamp","inParty":0,"caughtCount":1,"participationPct":0,"moves":[],"items":[],"abilities":[],"natures":[]},{"species":"Machoke","inParty":0,"caughtCount":2,"participationPct":0,"moves":[],"items":[],"abilities":[],"natures":[]},{"species":"Malamar","inParty":0,"caughtCount":1,"participationPct":0,"moves":[],"items":[],"abilities":[],"natures":[]},{"species":"Mankey","inParty":0,"caughtCount":1,"participationPct":0,"moves":[],"items":[],"abilities":[],"natures":[]}]},"battles":[{"eventId":"88c124ab-e9a0-48b0-bfa9-fa98488e7671","createdAt":"2026-03-05T06:45:04.717000Z","party":[{"species":"Tinkaton","moves":["Fake Out","Rock Slide","Play Rough","Gigaton Hammer"],"item":"Leftovers","ability":"Mold Breaker","nature":"Adamant"},{"species":"Heliolisk","moves":["Parabolic Charge","Volt Switch","Hyper Voice","Thunderbolt"],"item":"Magnet","ability":"Dry Skin","nature":"Timid"},{"species":"Magnezone","moves":["Thunderbolt","Volt Switch","Flash Cannon","Reflect"],"item":"Chople Berry","ability":"Analytic","nature":"Modest"},{"species":"Mudsdale","moves":["Earthquake","Bulldoze","Rock Slide","Heavy Slam"],"item":"Sitrus Berry","ability":"Stamina","nature":"Adamant"},{"species":"Torterra","moves":["Wood Hammer","Synthesis","Earthquake","Rock Slide"],"item":"Tanga Berry","ability":"Shell Armor","nature":"Adamant"},{"species":"Swanna","moves":["Hurricane","Roost","Hydro Pump","Flip Turn"],"item":"Sitrus Berry","ability":"No Guard","nature":"Timid"}],"boxPokemon":["Toedscool","Sewaddle","Mankey","Turtwig","Furret","Wingull","Lechonk","Seel","Gastly","Meowth","Grotle","Oinkologne","Leavanny","Nidorina","Nidoqueen","Ducklett","Pelipper","Haunter","Gyarados","Inkay","Kricketune","Malamar","Swanna","Primeape","Persian","Toedscruel","Golisopod","Dewgong","Magnezone","Heliolisk","Mudsdale","Torterra","Annihilape","Gengar","Bisharp","Darmanitan","Froslass","Cinderace","Quaquaval","Tinkaton","Escavalier","Heatmor","Ferrothorn"]},{"eventId":"49bcb390-e6ef-42e4-855a-20fcc2a78bc1","createdAt":"2026-02-25T03:56:05.188000Z","party":[{"species":"Luxray","moves":["Volt Switch","Ice Fang","Thunder Fang","Crunch"],"item":"Shuca Berry","ability":"Intimidate","nature":"Adamant"},{"species":"Stunfisk","moves":["Scald","Mud Shot","Rest","Thunderbolt"],"item":"Sitrus Berry","ability":"Static","nature":"Bold"},{"species":"Primarina","moves":["Encore","Flip Turn","Moonblast","Hyper Voice"],"item":"Sitrus Berry","ability":"Liquid Voice","nature":"Calm"},{"species":"Golisopod","moves":["Razor Shell","First Impression","Sucker Punch","Leech Life"],"item":"Sitrus Berry","ability":"Emergency Exit","nature":"Careful"},{"species":"Lilligant-Hisui","moves":["Leaf Blade","Sleep Powder","Recover","Drain Punch"],"item":"Chilan Berry","ability":"Chlorophyll","nature":"Jolly"},{"species":"Skarmory","moves":["Dual Wingbeat","Steel Wing","Roost","Slash"],"item":"","ability":"Sturdy","nature":"Naive"}],"boxPokemon":["Camerupt","Centiskorch","Drifblim","Incineroar","Inteleon","Torterra","Stunfisk","Primarina","Overqwil","Starmie","Mawile","Sirfetch\u2019d","Rapidash","Slowbro","Butterfree","Wigglytuff","Dubwool","Musharna","Illumise","Gengar","Luxray","Golisopod","Conkeldurr","Persian","Foongus","Skarmory","Spiritomb","Electivire"]},{"eventId":"12b794f9-1df8-441e-a45b-27d8a81a3724","createdAt":"2026-02-20T09:38:27.403000Z","party":[{"species":"Pikachu-Flying","moves":["Fake Out","Nuzzle","Air Slash","Thunderbolt"],"item":"Light Ball","ability":"Static","nature":"Timid"},{"species":"Clodsire","moves":["Toxic Spikes","Earthquake","Rock Slide","Toxic"],"item":"Black Sludge","ability":"Water Absorb","nature":"Careful"},{"species":"Slowbro","moves":["Slack Off","Toxic","Scald","Psychic"],"item":"Leftovers","ability":"Regenerator","nature":"Bold"},{"species":"Minun","moves":["Encore","Nuzzle","Double-Edge","Quick Attack"],"item":"Magnet","ability":"Galvanize","nature":"Jolly"},{"species":"Granbull","moves":["Thunder Fang","Fire Fang","Jaw Lock","Play Rough"],"item":"Sitrus Berry","ability":"Intimidate","nature":"Adamant"},{"species":"Exploud","moves":["Bulldoze","Hyper Voice","Crunch","Fire Fang"],"item":"Sitrus Berry","ability":"Soundproof","nature":"Modest"}],"boxPokemon":["Skeledirge","Slowbro","Mudsdale","Meowscarada","Altaria","Victreebel","Beedrill","Hatterene","Sawsbuck","Granbull","Swoobat","Starmie","Minun","Stunfisk","Galvantula","Ludicolo","Sharpedo","Wyrdeer","Delphox","Exploud","Revavroom","Clodsire","Pikachu"]},{"eventId":"0a3b3f5d-80c6-4d6b-b715-4ce17407a26e","createdAt":"2026-02-18T03:16:35.776000Z","party":[{"species":"Kilowattrel","moves":["Thunder Shock","Air Slash","Roost","Volt Switch"],"item":"Sharp Beak","ability":"Volt Absorb","nature":"Modest"},{"species":"Eldegoss","moves":["Cotton Spore","Hyper Voice","Synthesis","Giga Drain"],"item":"Sitrus Berry","ability":"Regenerator","nature":"Relaxed"},{"species":"Qwilfish","moves":["Bubble","Revenge","Tackle","Barb Barrage"],"item":"Sitrus Berry","ability":"Intimidate","nature":"Adamant"},{"species":"Gyarados","moves":["Bulldoze","Aqua Tail","Crunch","Ice Fang"],"item":"Sitrus Berry","ability":"Intimidate","nature":"Adamant"},{"species":"Dragalge","moves":["Hydro Pump","Water Pulse","Feint Attack","Sludge Bomb"],"item":"Black Sludge","ability":"Adaptability","nature":"Modest"},{"species":"Zebstrika","moves":["Spark","Discharge","Thunder Wave","Flame Wheel"],"item":"Sitrus Berry","ability":"Lightning Rod","nature":"Jolly"}],"boxPokemon":["Breloom","Luxray","Krookodile","Kilowattrel","Gardevoir","Emboar","Bronzong","Gyarados","Araquanid","Spidops","Dragalge","Bibarel","Qwilfish","Grumpig","Swanna","Eldegoss","Zebstrika","Cacturne","Masquerain","Slowbro","Machoke"]},{"eventId":"e88d6cc9-8218-4222-9e25-64b31cbf83a9","createdAt":"2026-02-09T03:19:12.501000Z","party":[{"species":"Luxray","moves":["Thunder Fang","Volt Switch","Sucker Punch","Psychic Fangs"],"item":"Luxrite","ability":"Intimidate","nature":"Adamant"},{"species":"Luxray-Mega","moves":["Thunder Fang","Volt Switch","Sucker Punch","Psychic Fangs"],"item":"","ability":"Strong Jaw","nature":"Adamant"},{"species":"Meowscarada","moves":["U-turn","Play Rough","Flower Trick","Protect"],"item":"Miracle Seed","ability":"Protean","nature":"Jolly"},{"species":"Lapras","moves":["Ice Shard","Dragon Pulse","Wish","Scald"],"item":"Leftovers","ability":"Water Absorb","nature":"Modest"},{"species":"Rhyperior","moves":["Rock Slide","Hammer Arm","Bulldoze","Earthquake"],"item":"Sitrus Berry","ability":"Solid Rock","nature":"Adamant"},{"species":"Scizor","moves":["Bullet Punch","Pounce","Iron Head","Protect"],"item":"Sitrus Berry","ability":"Technician","nature":"Adamant"}],"boxPokemon":["Delphox","Nidoking","Quaquaval","Rapidash","Scizor","Swanna","Swellow","Starmie","Delibird","Rhyperior","Salazzle","Golem","Fearow","Slowbro","Torterra","Gardevoir","Blastoise","Heracross","Staraptor","Empoleon","Tinkaton","Lapras","Dewgong","Chesnaught","Stunfisk","Granbull","Sceptile","Luxray","Serperior","Meowscarada","Pelipper"]},{"eventId":"b7cec683-72e3-4796-84bc-128f0e1f3bfd","createdAt":"2026-01-26T23:57:25.873000Z","party":[{"species":"Giratina","moves":["Shadow Ball","Psychic","Earth Power","Protect"],"item":"Leftovers","ability":"Pressure","nature":"Modest"},{"species":"Slaking","moves":["Body Slam","Hammer Arm","Sucker Punch","Slack Off"],"item":"Silk Scarf","ability":"Shadow Shield","nature":"Adamant"},{"species":"Copperajah","moves":["Heavy Slam","Body Press","Rock Tomb","Bulldoze"],"item":"Chople Berry","ability":"Gorilla Tactics","nature":"Adamant"},{"species":"Scyther","moves":["Brick Break","Wing Attack","Psycho Cut","U-turn"],"item":"Eviolite","ability":"Fur Coat","nature":"Adamant"},{"species":"Braviary-Hisui","moves":["Esper Wing","Air Slash","Aura Sphere","U-turn"],"item":"Charti Berry","ability":"Tablets of Ruin","nature":"Modest"},{"species":"Conkeldurr","moves":["Drain Punch","Rock Tomb","Low Kick","Mach Punch"],"item":"Payapa Berry","ability":"Primordial Sea","nature":"Adamant"}],"boxPokemon":["Gigalith","Swalot","Simipour","Chimchar","Regigigas","Regieleki","Conkeldurr","Cubchoo","Corsola","Overqwil","Barboach","Samurott","Electabuzz","Horsea","Flygon","Slaking","Copperajah","Beedrill","Blastoise","Giratina","Machoke","Machamp","Electivire","Scyther","Glastrier","Greninja"]}]}
