{"title":"Vintage White Plus","generatedAt":"2026-04-16T19:12:54.015134Z","historyLimit":100,"trainer":{"displayName":"PkMn Trainer Cynthia","usageKey":"567","leadLevel":100,"maxLevel":100,"isBoss":false,"partySize":6,"trId":567},"summary":{"totalBattles":1,"topPokemon":[{"species":"Armaldo","inParty":1,"caughtCount":1,"participationPct":100,"moves":[{"name":"Megahorn","count":1,"pct":100},{"name":"Rock Slide","count":1,"pct":100},{"name":"Superpower","count":1,"pct":100},{"name":"X-Scissor","count":1,"pct":100}],"items":[],"abilities":[{"name":"Battle Armor","count":1,"pct":100}],"natures":[{"name":"Lonely","count":1,"pct":100}]},{"species":"Banette","inParty":1,"caughtCount":1,"participationPct":100,"moves":[{"name":"Knock Off","count":1,"pct":100},{"name":"Night Daze","count":1,"pct":100},{"name":"Sucker Punch","count":1,"pct":100},{"name":"Will-O-Wisp","count":1,"pct":100}],"items":[{"name":"Leftovers","count":1,"pct":100}],"abilities":[{"name":"Prankster","count":1,"pct":100}],"natures":[{"name":"Hardy","count":1,"pct":100}]},{"species":"Crobat","inParty":1,"caughtCount":1,"participationPct":100,"moves":[{"name":"Brave Bird","count":1,"pct":100},{"name":"Cross Poison","count":1,"pct":100},{"name":"Fly","count":1,"pct":100},{"name":"U-turn","count":1,"pct":100}],"items":[],"abilities":[{"name":"Sniper","count":1,"pct":100}],"natures":[{"name":"Adamant","count":1,"pct":100}]},{"species":"Golduck","inParty":1,"caughtCount":1,"participationPct":100,"moves":[{"name":"Ice Beam","count":1,"pct":100},{"name":"Protect","count":1,"pct":100},{"name":"Psycho Boost","count":1,"pct":100},{"name":"Surf","count":1,"pct":100}],"items":[{"name":"Choice Scarf","count":1,"pct":100}],"abilities":[{"name":"Cloud Nine","count":1,"pct":100}],"natures":[{"name":"Modest","count":1,"pct":100}]},{"species":"Maractus","inParty":1,"caughtCount":1,"participationPct":100,"moves":[{"name":"Giga Drain","count":1,"pct":100},{"name":"Leaf Storm","count":1,"pct":100},{"name":"Sunny Day","count":1,"pct":100},{"name":"Synthesis","count":1,"pct":100}],"items":[{"name":"Lum Berry","count":1,"pct":100}],"abilities":[{"name":"Storm Drain","count":1,"pct":100}],"natures":[{"name":"Modest","count":1,"pct":100}]},{"species":"Unfezant","inParty":1,"caughtCount":1,"participationPct":100,"moves":[{"name":"Air Slash","count":1,"pct":100},{"name":"Aura Sphere","count":1,"pct":100},{"name":"Heat Wave","count":1,"pct":100},{"name":"U-turn","count":1,"pct":100}],"items":[{"name":"Fighting Gem","count":1,"pct":100}],"abilities":[{"name":"Scrappy","count":1,"pct":100}],"natures":[{"name":"Bold","count":1,"pct":100}]},{"species":"Accelgor","inParty":0,"caughtCount":1,"participationPct":0,"moves":[],"items":[],"abilities":[],"natures":[]},{"species":"Aerodactyl","inParty":0,"caughtCount":1,"participationPct":0,"moves":[],"items":[],"abilities":[],"natures":[]},{"species":"Anorith","inParty":0,"caughtCount":1,"participationPct":0,"moves":[],"items":[],"abilities":[],"natures":[]},{"species":"Arcanine","inParty":0,"caughtCount":1,"participationPct":0,"moves":[],"items":[],"abilities":[],"natures":[]},{"species":"Archen","inParty":0,"caughtCount":1,"participationPct":0,"moves":[],"items":[],"abilities":[],"natures":[]},{"species":"Archeops","inParty":0,"caughtCount":1,"participationPct":0,"moves":[],"items":[],"abilities":[],"natures":[]},{"species":"Bagon","inParty":0,"caughtCount":1,"participationPct":0,"moves":[],"items":[],"abilities":[],"natures":[]},{"species":"Bisharp","inParty":0,"caughtCount":1,"participationPct":0,"moves":[],"items":[],"abilities":[],"natures":[]},{"species":"Camerupt","inParty":0,"caughtCount":1,"participationPct":0,"moves":[],"items":[],"abilities":[],"natures":[]},{"species":"Cloyster","inParty":0,"caughtCount":1,"participationPct":0,"moves":[],"items":[],"abilities":[],"natures":[]},{"species":"Dugtrio","inParty":0,"caughtCount":1,"participationPct":0,"moves":[],"items":[],"abilities":[],"natures":[]},{"species":"Electrode","inParty":0,"caughtCount":1,"participationPct":0,"moves":[],"items":[],"abilities":[],"natures":[]},{"species":"Emboar","inParty":0,"caughtCount":1,"participationPct":0,"moves":[],"items":[],"abilities":[],"natures":[]},{"species":"Fearow","inParty":0,"caughtCount":1,"participationPct":0,"moves":[],"items":[],"abilities":[],"natures":[]},{"species":"Flygon","inParty":0,"caughtCount":1,"participationPct":0,"moves":[],"items":[],"abilities":[],"natures":[]},{"species":"Frillish","inParty":0,"caughtCount":1,"participationPct":0,"moves":[],"items":[],"abilities":[],"natures":[]},{"species":"Gliscor","inParty":0,"caughtCount":1,"participationPct":0,"moves":[],"items":[],"abilities":[],"natures":[]},{"species":"Golem","inParty":0,"caughtCount":1,"participationPct":0,"moves":[],"items":[],"abilities":[],"natures":[]},{"species":"Grovyle","inParty":0,"caughtCount":1,"participationPct":0,"moves":[],"items":[],"abilities":[],"natures":[]},{"species":"Gyarados","inParty":0,"caughtCount":1,"participationPct":0,"moves":[],"items":[],"abilities":[],"natures":[]},{"species":"Hariyama","inParty":0,"caughtCount":1,"participationPct":0,"moves":[],"items":[],"abilities":[],"natures":[]},{"species":"Hitmontop","inParty":0,"caughtCount":1,"participationPct":0,"moves":[],"items":[],"abilities":[],"natures":[]},{"species":"Jellicent","inParty":0,"caughtCount":1,"participationPct":0,"moves":[],"items":[],"abilities":[],"natures":[]},{"species":"Kecleon","inParty":0,"caughtCount":1,"participationPct":0,"moves":[],"items":[],"abilities":[],"natures":[]},{"species":"Kingler","inParty":0,"caughtCount":1,"participationPct":0,"moves":[],"items":[],"abilities":[],"natures":[]},{"species":"Kyurem","inParty":0,"caughtCount":1,"participationPct":0,"moves":[],"items":[],"abilities":[],"natures":[]},{"species":"Lanturn","inParty":0,"caughtCount":1,"participationPct":0,"moves":[],"items":[],"abilities":[],"natures":[]},{"species":"Lapras","inParty":0,"caughtCount":1,"participationPct":0,"moves":[],"items":[],"abilities":[],"natures":[]},{"species":"Larvesta","inParty":0,"caughtCount":1,"participationPct":0,"moves":[],"items":[],"abilities":[],"natures":[]},{"species":"Luvdisc","inParty":0,"caughtCount":1,"participationPct":0,"moves":[],"items":[],"abilities":[],"natures":[]},{"species":"Luxray","inParty":0,"caughtCount":1,"participationPct":0,"moves":[],"items":[],"abilities":[],"natures":[]},{"species":"Medicham","inParty":0,"caughtCount":1,"participationPct":0,"moves":[],"items":[],"abilities":[],"natures":[]},{"species":"Mienshao","inParty":0,"caughtCount":1,"participationPct":0,"moves":[],"items":[],"abilities":[],"natures":[]},{"species":"Moltres","inParty":0,"caughtCount":1,"participationPct":0,"moves":[],"items":[],"abilities":[],"natures":[]},{"species":"Oshawott","inParty":0,"caughtCount":1,"participationPct":0,"moves":[],"items":[],"abilities":[],"natures":[]},{"species":"Pawniard","inParty":0,"caughtCount":1,"participationPct":0,"moves":[],"items":[],"abilities":[],"natures":[]},{"species":"Pelipper","inParty":0,"caughtCount":1,"participationPct":0,"moves":[],"items":[],"abilities":[],"natures":[]},{"species":"Pidgeot","inParty":0,"caughtCount":1,"participationPct":0,"moves":[],"items":[],"abilities":[],"natures":[]},{"species":"Pidgeotto","inParty":0,"caughtCount":1,"participationPct":0,"moves":[],"items":[],"abilities":[],"natures":[]},{"species":"Poliwrath","inParty":0,"caughtCount":1,"participationPct":0,"moves":[],"items":[],"abilities":[],"natures":[]},{"species":"Probopass","inParty":0,"caughtCount":1,"participationPct":0,"moves":[],"items":[],"abilities":[],"natures":[]},{"species":"Rayquaza","inParty":0,"caughtCount":1,"participationPct":0,"moves":[],"items":[],"abilities":[],"natures":[]},{"species":"Salamence","inParty":0,"caughtCount":1,"participationPct":0,"moves":[],"items":[],"abilities":[],"natures":[]},{"species":"Samurott","inParty":0,"caughtCount":1,"participationPct":0,"moves":[],"items":[],"abilities":[],"natures":[]},{"species":"Sandslash","inParty":0,"caughtCount":1,"participationPct":0,"moves":[],"items":[],"abilities":[],"natures":[]},{"species":"Sawsbuck","inParty":0,"caughtCount":1,"participationPct":0,"moves":[],"items":[],"abilities":[],"natures":[]},{"species":"Sceptile","inParty":0,"caughtCount":1,"participationPct":0,"moves":[],"items":[],"abilities":[],"natures":[]},{"species":"Scizor","inParty":0,"caughtCount":1,"participationPct":0,"moves":[],"items":[],"abilities":[],"natures":[]},{"species":"Seviper","inParty":0,"caughtCount":1,"participationPct":0,"moves":[],"items":[],"abilities":[],"natures":[]},{"species":"Shellder","inParty":0,"caughtCount":1,"participationPct":0,"moves":[],"items":[],"abilities":[],"natures":[]},{"species":"Smeargle","inParty":0,"caughtCount":1,"participationPct":0,"moves":[],"items":[],"abilities":[],"natures":[]},{"species":"Starmie","inParty":0,"caughtCount":1,"participationPct":0,"moves":[],"items":[],"abilities":[],"natures":[]},{"species":"Swampert","inParty":0,"caughtCount":1,"participationPct":0,"moves":[],"items":[],"abilities":[],"natures":[]},{"species":"Tepig","inParty":0,"caughtCount":1,"participationPct":0,"moves":[],"items":[],"abilities":[],"natures":[]},{"species":"Thundurus","inParty":0,"caughtCount":1,"participationPct":0,"moves":[],"items":[],"abilities":[],"natures":[]},{"species":"Typhlosion","inParty":0,"caughtCount":1,"participationPct":0,"moves":[],"items":[],"abilities":[],"natures":[]},{"species":"Unown","inParty":0,"caughtCount":1,"participationPct":0,"moves":[],"items":[],"abilities":[],"natures":[]},{"species":"Volcarona","inParty":0,"caughtCount":1,"participationPct":0,"moves":[],"items":[],"abilities":[],"natures":[]},{"species":"Wailmer","inParty":0,"caughtCount":1,"participationPct":0,"moves":[],"items":[],"abilities":[],"natures":[]},{"species":"Wailord","inParty":0,"caughtCount":1,"participationPct":0,"moves":[],"items":[],"abilities":[],"natures":[]},{"species":"Weavile","inParty":0,"caughtCount":1,"participationPct":0,"moves":[],"items":[],"abilities":[],"natures":[]},{"species":"Zapdos","inParty":0,"caughtCount":1,"participationPct":0,"moves":[],"items":[],"abilities":[],"natures":[]}]},"battles":[{"eventId":"25d678d6-6fae-43a0-849d-6326e3aaebd7","createdAt":"2026-02-14T11:02:38.729000Z","party":[{"species":"Unfezant","moves":["Aura Sphere","Air Slash","Heat Wave","U-turn"],"item":"Fighting Gem","ability":"Scrappy","nature":"Bold"},{"species":"Maractus","moves":["Leaf Storm","Sunny Day","Giga Drain","Synthesis"],"item":"Lum Berry","ability":"Storm Drain","nature":"Modest"},{"species":"Crobat","moves":["Fly","Cross Poison","Brave Bird","U-turn"],"item":"","ability":"Sniper","nature":"Adamant"},{"species":"Golduck","moves":["Surf","Protect","Psycho Boost","Ice Beam"],"item":"Choice Scarf","ability":"Cloud Nine","nature":"Modest"},{"species":"Banette","moves":["Sucker Punch","Night Daze","Knock Off","Will-O-Wisp"],"item":"Leftovers","ability":"Prankster","nature":"Hardy"},{"species":"Armaldo","moves":["X-Scissor","Superpower","Megahorn","Rock Slide"],"item":"","ability":"Battle Armor","nature":"Lonely"}],"boxPokemon":["Golduck","Hitmontop","Kecleon","Hariyama","Grovyle","Fearow","Kingler","Camerupt","Pidgeotto","Lanturn","Luvdisc","Anorith","Armaldo","Pidgeot","Sceptile","Scizor","Typhlosion","Swampert","Gyarados","Electrode","Aerodactyl","Weavile","Arcanine","Banette","Probopass","Dugtrio","Zapdos","Crobat","Golem","Smeargle","Lapras","Medicham","Starmie","Pelipper","Poliwrath","Wailmer","Shellder","Bagon","Salamence","Wailord","Cloyster","Seviper","Flygon","Thundurus","Gliscor","Moltres","Sandslash","Unown","Luxray","Pawniard","Frillish","Oshawott","Mienshao","Unfezant","Tepig","Larvesta","Maractus","Sawsbuck","Accelgor","Archen","Rayquaza","Volcarona","Kyurem","Bisharp","Jellicent","Samurott","Emboar","Archeops"]}]}
